scholar
setup.cfg
setup.py
Agora_Scholar.egg-info/PKG-INFO
Agora_Scholar.egg-info/SOURCES.txt
Agora_Scholar.egg-info/dependency_links.txt
Agora_Scholar.egg-info/namespace_packages.txt
Agora_Scholar.egg-info/requires.txt
Agora_Scholar.egg-info/top_level.txt
agora/__init__.py
agora/scholar/__init__.py
agora/scholar/api.py
agora/scholar/metadata.json
agora/scholar/actions/__init__.py
agora/scholar/actions/query.py
agora/scholar/actions/stream.py
agora/scholar/daemons/__init__.py
agora/scholar/daemons/fragment.py
agora/scholar/server/__init__.py
agora/scholar/server/config.py