Metadata-Version: 1.1
Name: Agora-Scholar
Version: 0.2.0
Summary: The service responsible for providing access to data fragments from a Linked Data Platform powered by Agora
Home-page: https://github.com/smartdeveloperhub/agora-stoa.git
Author: Fernando Serena
Author-email: fernando.serena@centeropenmiddleware.com
License: Apache 2
Download-URL: https://github.com/smartdeveloperhub/agora-scholar/tarball/0.2.0
Keywords: linked-data,ontology,fragments
Platform: UNKNOWN
